pytest_xdist_worker_stats/__init__.py
pytest_xdist_worker_stats/options.py
pytest_xdist_worker_stats/plugin.py
pytest_xdist_worker_stats-0.3.1.dist-info/METADATA
pytest_xdist_worker_stats-0.3.1.dist-info/WHEEL
pytest_xdist_worker_stats-0.3.1.dist-info/entry_points.txt
pytest_xdist_worker_stats-0.3.1.dist-info/licenses/LICENSE
pytest_xdist_worker_stats-0.3.1.dist-info/RECORD
